testclick/__init__.py
testclick/helloworld.py
testclick-0.1.0.dist-info/entry_points.txt
testclick-0.1.0.dist-info/WHEEL
testclick-0.1.0.dist-info/METADATA
testclick-0.1.0.dist-info/RECORD
